[
  {
    "EventType": "HighWater",
    "DateTime": "2023-12-16T00:50:00",
    "IsApproximateTime": false,
    "Height": 6.36084607457618,
    "IsApproximateHeight": false,
    "Filtered": false,
    "Date": "2023-12-16T00:00:00"
  },
  {
    "EventType": "LowWater",
    "DateTime": "2023-12-16T07:13:00",
    "IsApproximateTime": false,
    "Height": 1.1387331105753853,
    "IsApproximateHeight": false,
    "Filtered": false,
    "Date": "2023-12-16T00:00:00"
  },
  {
    "EventType": "HighWater",
    "DateTime": "2023-12-16T13:04:00",
    "IsApproximateTime": false,
    "Height": 6.303178360225942,
    "IsApproximateHeight": false,
    "Filtered": false,
    "Date": "2023-12-16T00:00:00"
  },
  {
    "EventType": "LowWater",
    "DateTime": "2023-12-16T19:37:00",
    "IsApproximateTime": false,
    "Height": 0.9800089647884018,
    "IsApproximateHeight": false,
    "Filtered": false,
    "Date": "2023-12-16T00:00:00"
  },
  {
    "EventType": "HighWater",
    "DateTime": "2023-12-17T01:37:00",
    "IsApproximateTime": false,
    "Height": 6.2822382052265,
    "IsApproximateHeight": false,
    "Filtered": false,
    "Date": "2023-12-17T00:00:00"
  },
  {
    "EventType": "LowWater",
    "DateTime": "2023-12-17T08:01:00",
    "IsApproximateTime": false,
    "Height": 1.2103574325034796,
    "IsApproximateHeight": false,
    "Filtered": false,
    "Date": "2023-12-17T00:00:00"
  },
  {
    "EventType": "HighWater",
    "DateTime": "2023-12-17T13:52:00",
    "IsApproximateTime": false,
    "Height": 6.139328073813636,
    "IsApproximateHeight": false,
    "Filtered": false,
    "Date": "2023-12-17T00:00:00"
  },
  {
    "EventType": "LowWater",
    "DateTime": "2023-12-17T20:27:00",
    "IsApproximateTime": false,
    "Height": 1.0822911193899634,
    "IsApproximateHeight": false,
    "Filtered": false,
    "Date": "2023-12-17T00:00:00"
  }
]
