[
  {
    "EventType": "HighWater",
    "DateTime": "2025-07-03T04:21:00",
    "IsApproximateTime": false,
    "Height": 5.2415749511704535,
    "IsApproximateHeight": false,
    "Filtered": false,
    "Date": "2025-07-03T00:00:00"
  },
  {
    "EventType": "LowWater",
    "DateTime": "2025-07-03T10:37:00",
    "IsApproximateTime": false,
    "Height": 1.8661011493258102,
    "IsApproximateHeight": false,
    "Filtered": false,
    "Date": "2025-07-03T00:00:00"
  },
  {
    "EventType": "HighWater",
    "DateTime": "2025-07-03T16:52:00",
    "IsApproximateTime": false,
    "Height": 5.4327047675751921,
    "IsApproximateHeight": false,
    "Filtered": false,
    "Date": "2025-07-03T00:00:00"
  },
  {
    "EventType": "LowWater",
    "DateTime": "2025-07-03T23:11:00",
    "IsApproximateTime": false,
    "Height": 2.0626115500891475,
    "IsApproximateHeight": false,
    "Filtered": false,
    "Date": "2025-07-03T00:00:00"
  },
  {
    "EventType": "HighWater",
    "DateTime": "2025-07-04T05:19:00",
    "IsApproximateTime": false,
    "Height": 5.0666755213805477,
    "IsApproximateHeight": false,
    "Filtered": false,
    "Date": "2025-07-04T00:00:00"
  },
  {
    "EventType": "LowWater",
    "DateTime": "2025-07-04T11:35:00",
    "IsApproximateTime": false,
    "Height": 2.0548379896523361,
    "IsApproximateHeight": false,
    "Filtered": false,
    "Date": "2025-07-04T00:00:00"
  },
  {
    "EventType": "HighWater",
    "DateTime": "2025-07-04T17:49:00",
    "IsApproximateTime": false,
    "Height": 5.2849441085877915,
    "IsApproximateHeight": false,
    "Filtered": false,
    "Date": "2025-07-04T00:00:00"
  }
]
