{
  "hours": [
    {
      "airTemperature": {
        "ecmwf": 7.7,
        "ecmwf:aifs": 7.97,
        "noaa": 5.47,
        "sg": 7.7
      },
      "currentDirection": {
        "ecmwf": 52.84,
        "metno": 28.36,
        "meto": 74.2,
        "noaa": 86.71,
        "sg": 28.36
      },
      "currentSpeed": {
        "ecmwf": 0.03,
        "metno": 0.35,
        "meto": 0.16,
        "noaa": 0.09,
        "sg": 0.35
      },
      "gust": {
        "ecmwf": 7.53,
        "noaa": 4.23,
        "sg": 7.53
      },
      "time": "2026-03-04T04:00:00+00:00",
      "visibility": {
        "noaa": 24.13,
        "sg": 24.13
      },
      "waterTemperature": {
        "metno": 9.54,
        "meto": 9.19,
        "noaa": 9.01,
        "sg": 9.54
      },
      "waveDirection": {
        "ecmwf": 135.73,
        "meteo": 264.81,
        "metno": 190.48,
        "noaa": 76.78,
        "sg": 190.48
      },
      "waveHeight": {
        "dwd": 0.52,
        "ecmwf": 0.44,
        "meteo": 0.67,
        "metno": 0.26,
        "noaa": 0.78,
        "sg": 0.26
      },
      "wavePeriod": {
        "ecmwf": 2.42,
        "meteo": 3.5,
        "noaa": 4.07,
        "sg": 2.42
      },
      "windDirection": {
        "dwd": 51.63,
        "ecmwf": 62.19,
        "ecmwf:aifs": 70.63,
        "noaa": 66.29,
        "sg": 62.19
      },
      "windSpeed": {
        "dwd": 3.11,
        "ecmwf": 5.02,
        "ecmwf:aifs": 5.97,
        "noaa": 2.65,
        "sg": 5.02
      }
    },
    {
      "airTemperature": {
        "ecmwf": 7.67,
        "ecmwf:aifs": 7.97,
        "noaa": 5.51,
        "sg": 7.67
      },
      "currentDirection": {
        "ecmwf": 50.05,
        "metno": 26.15,
        "meto": 76.27,
        "noaa": 86.83,
        "sg": 26.15
      },
      "currentSpeed": {
        "ecmwf": 0.02,
        "metno": 0.18,
        "meto": 0.15,
        "noaa": 0.09,
        "sg": 0.18
      },
      "gust": {
        "ecmwf": 7.53,
        "noaa": 3.15,
        "sg": 7.53
      },
      "time": "2026-03-04T05:00:00+00:00",
      "visibility": {
        "noaa": 24.14,
        "sg": 24.14
      },
      "waterTemperature": {
        "metno": 9.54,
        "meto": 9.18,
        "noaa": 9.0,
        "sg": 9.54
      },
      "waveDirection": {
        "ecmwf": 121.96,
        "meteo": 262.53,
        "metno": 183.39,
        "noaa": 76.31,
        "sg": 183.39
      },
      "waveHeight": {
        "dwd": 0.5,
        "ecmwf": 0.45,
        "meteo": 0.65,
        "metno": 0.24,
        "noaa": 0.74,
        "sg": 0.24
      },
      "wavePeriod": {
        "ecmwf": 2.37,
        "meteo": 3.5,
        "noaa": 3.99,
        "sg": 2.37
      },
      "windDirection": {
        "dwd": 51.16,
        "ecmwf": 67.95,
        "ecmwf:aifs": 72.06,
        "noaa": 70.84,
        "sg": 67.95
      },
      "windSpeed": {
        "dwd": 3.14,
        "ecmwf": 5.24,
        "ecmwf:aifs": 5.79,
        "noaa": 2.37,
        "sg": 5.24
      }
    }
  ],
  "meta": {
    "cost": 1,
    "dailyQuota": 10,
    "end": "2026-03-04 05:00",
    "lat": 50.8141883,
    "lng": -0.1416837,
    "params": [
      "waterTemperature",
      "windSpeed",
      "windDirection",
      "gust",
      "waveHeight",
      "waveDirection",
      "wavePeriod",
      "visibility",
      "currentDirection",
      "currentSpeed",
      "airTemperature"
    ],
    "requestCount": 2,
    "start": "2026-03-04 04:00"
  }
}
