{
  "hours": [
    {
      "airTemperature": {
        "dwd": 17.63,
        "noaa": 18.41,
        "sg": 17.63
      },
      "currentDirection": {
        "meto": 253.36,
        "sg": 253.36
      },
      "currentSpeed": {
        "meto": 0.26,
        "sg": 0.26
      },
      "gust": {
        "dwd": 22.83,
        "noaa": 19.1,
        "sg": 22.83
      },
      "time": "2023-07-15T15:00:00+00:00",
      "visibility": {
        "noaa": 24.14,
        "sg": 24.14
      },
      "waterTemperature": {
        "meto": 17.69,
        "noaa": 20.35,
        "sg": 17.69
      },
      "waveDirection": {
        "icon": 223.73,
        "meteo": 238.13,
        "noaa": 241.48,
        "sg": 238.13
      },
      "waveHeight": {
        "dwd": 2.37,
        "icon": 2.7,
        "meteo": 1.63,
        "noaa": 2.97,
        "sg": 1.63
      },
      "wavePeriod": {
        "icon": 6.7,
        "meteo": 4.65,
        "noaa": 8.08,
        "sg": 4.65
      },
      "windDirection": {
        "icon": 226.1,
        "noaa": 224.44,
        "sg": 226.1
      },
      "windSpeed": {
        "icon": 12.8,
        "noaa": 12.17,
        "sg": 12.8
      }
    },
    {
      "airTemperature": {
        "dwd": 17.59,
        "noaa": 17.94,
        "sg": 17.59
      },
      "currentDirection": {
        "meto": 254,
        "sg": 254
      },
      "currentSpeed": {
        "meto": 0.28,
        "sg": 0.28
      },
      "gust": {
        "dwd": 23.12,
        "noaa": 19.02,
        "sg": 23.12
      },
      "time": "2023-07-15T16:00:00+00:00",
      "visibility": {
        "noaa": 24.14,
        "sg": 24.14
      },
      "waterTemperature": {
        "meto": 17.72,
        "noaa": 19.39,
        "sg": 17.72
      },
      "waveDirection": {
        "icon": 223.89,
        "meteo": 239.02,
        "noaa": 241.73,
        "sg": 239.02
      },
      "waveHeight": {
        "dwd": 2.37,
        "icon": 2.8,
        "meteo": 1.68,
        "noaa": 2.96,
        "sg": 1.68
      },
      "wavePeriod": {
        "icon": 6.79,
        "meteo": 4.68,
        "noaa": 8.14,
        "sg": 4.68
      },
      "windDirection": {
        "icon": 226.04,
        "noaa": 225.25,
        "sg": 226.04
      },
      "windSpeed": {
        "icon": 13.29,
        "noaa": 11.61,
        "sg": 13.29
      }
    }
  ],
  "meta": {
    "cost": 1,
    "dailyQuota": 10,
    "end": "2023-07-15 16:02",
    "lat": 50.8141883,
    "lng": -0.1416837,
    "params": [
      "waterTemperature",
      "windSpeed",
      "windDirection",
      "gust",
      "waveHeight",
      "waveDirection",
      "wavePeriod",
      "visibility",
      "currentDirection",
      "currentSpeed",
      "airTemperature"
    ],
    "requestCount": 6,
    "start": "2023-07-15 15:00"
  }
}
