{
  "hours": [
    {
      "airTemperature": {
        "dwd": 16.37,
        "noaa": 14.83,
        "sg": 16.37
      },
      "currentDirection": {
        "meto": 262.43,
        "sg": 262.43
      },
      "currentSpeed": {
        "meto": 0.16,
        "sg": 0.16
      },
      "gust": {
        "dwd": 24.61,
        "noaa": 14.94,
        "sg": 24.61
      },
      "time": "2024-09-30T06:00:00+00:00",
      "visibility": {
        "noaa": 15.16,
        "sg": 15.16
      },
      "waterTemperature": {
        "meto": 16.14,
        "noaa": 14.08,
        "sg": 16.14
      },
      "waveDirection": {
        "meteo": 231.62,
        "noaa": 236.48,
        "sg": 231.62
      },
      "waveHeight": {
        "dwd": 2.73,
        "meteo": 3.56,
        "noaa": 3.53,
        "sg": 3.56
      },
      "wavePeriod": {
        "meteo": 6.31,
        "noaa": 8.26,
        "sg": 6.31
      },
      "windDirection": {
        "noaa": 209.07,
        "sg": 209.07
      },
      "windSpeed": {
        "noaa": 8.52,
        "sg": 8.52
      }
    },
    {
      "airTemperature": {
        "dwd": 16.22,
        "noaa": 14.93,
        "sg": 16.22
      },
      "currentDirection": {
        "meto": 261.38,
        "sg": 261.38
      },
      "currentSpeed": {
        "meto": 0.16,
        "sg": 0.16
      },
      "gust": {
        "dwd": 24.15,
        "noaa": 14.35,
        "sg": 24.15
      },
      "time": "2024-09-30T07:00:00+00:00",
      "visibility": {
        "noaa": 11.92,
        "sg": 11.92
      },
      "waterTemperature": {
        "meto": 16.14,
        "noaa": 14.4,
        "sg": 16.14
      },
      "waveDirection": {
        "meteo": 236.51,
        "noaa": 238.43,
        "sg": 236.51
      },
      "waveHeight": {
        "dwd": 2.78,
        "meteo": 3.95,
        "noaa": 3.76,
        "sg": 3.95
      },
      "wavePeriod": {
        "meteo": 6.69,
        "noaa": 8.61,
        "sg": 6.69
      },
      "windDirection": {
        "noaa": 212.73,
        "sg": 212.73
      },
      "windSpeed": {
        "noaa": 8.37,
        "sg": 8.37
      }
    }
  ],
  "meta": {
    "cost": 1,
    "dailyQuota": 10,
    "end": "2024-09-30 07:13",
    "lat": 50.8141883,
    "lng": -0.1416837,
    "params": [
      "waterTemperature",
      "windSpeed",
      "windDirection",
      "gust",
      "waveHeight",
      "waveDirection",
      "wavePeriod",
      "visibility",
      "currentDirection",
      "currentSpeed",
      "airTemperature"
    ],
    "requestCount": 3,
    "start": "2024-09-30 06:00"
  }
}
