{
  "hours": [
    {
      "airTemperature": {
        "dwd": 16.32,
        "noaa": 16.18,
        "sg": 16.32
      },
      "currentDirection": {
        "meto": 265.55,
        "sg": 265.55
      },
      "currentSpeed": {
        "meto": 0.15,
        "sg": 0.15
      },
      "gust": {
        "dwd": 20.48,
        "noaa": 18.88,
        "sg": 20.48
      },
      "time": "2024-10-20T12:00:00+00:00",
      "visibility": {
        "noaa": 24.14,
        "sg": 24.14
      },
      "waterTemperature": {
        "meto": 15.33,
        "noaa": 15.75,
        "sg": 15.33
      },
      "waveDirection": {
        "meteo": 201.99,
        "noaa": 207.76,
        "sg": 201.99
      },
      "waveHeight": {
        "dwd": 2.67,
        "meteo": 2.23,
        "noaa": 2.63,
        "sg": 2.23
      },
      "wavePeriod": {
        "meteo": 4.8,
        "noaa": 6.79,
        "sg": 4.8
      },
      "windDirection": {
        "noaa": 198.8,
        "sg": 198.8
      },
      "windSpeed": {
        "noaa": 11.32,
        "sg": 11.32
      }
    },
    {
      "airTemperature": {
        "dwd": 16.41,
        "noaa": 16.09,
        "sg": 16.41
      },
      "currentDirection": {
        "meto": 262.72,
        "sg": 262.72
      },
      "currentSpeed": {
        "meto": 0.17,
        "sg": 0.17
      },
      "gust": {
        "dwd": 20.34,
        "noaa": 18.04,
        "sg": 20.34
      },
      "time": "2024-10-20T13:00:00+00:00",
      "visibility": {
        "noaa": 24.14,
        "sg": 24.14
      },
      "waterTemperature": {
        "meto": 15.33,
        "noaa": 15.62,
        "sg": 15.33
      },
      "waveDirection": {
        "meteo": 209.21,
        "noaa": 216.08,
        "sg": 209.21
      },
      "waveHeight": {
        "dwd": 2.61,
        "meteo": 2.36,
        "noaa": 2.71,
        "sg": 2.36
      },
      "wavePeriod": {
        "meteo": 4.96,
        "noaa": 7.08,
        "sg": 4.96
      },
      "windDirection": {
        "noaa": 209.37,
        "sg": 209.37
      },
      "windSpeed": {
        "noaa": 10.69,
        "sg": 10.69
      }
    }
  ],
  "meta": {
    "cost": 1,
    "dailyQuota": 10,
    "end": "2024-10-20 13:24",
    "lat": 50.8141883,
    "lng": -0.1416837,
    "params": [
      "waterTemperature",
      "windSpeed",
      "windDirection",
      "gust",
      "waveHeight",
      "waveDirection",
      "wavePeriod",
      "visibility",
      "currentDirection",
      "currentSpeed",
      "airTemperature"
    ],
    "requestCount": 5,
    "start": "2024-10-20 12:00"
  }
}
