{
  "hours": [
    {
      "airTemperature": {
        "dwd": 8.33,
        "noaa": 4.82,
        "sg": 8.33
      },
      "currentDirection": {
        "meto": 264.76,
        "sg": 264.76
      },
      "currentSpeed": {
        "meto": 0.13,
        "sg": 0.13
      },
      "gust": {
        "dwd": 11.86,
        "noaa": 12.04,
        "sg": 11.86
      },
      "time": "2024-04-28T12:00:00+00:00",
      "visibility": {
        "noaa": 0.08,
        "sg": 0.08
      },
      "waterTemperature": {
        "meto": 10.92,
        "noaa": 5.09,
        "sg": 10.92
      },
      "waveDirection": {
        "icon": 237.77,
        "meteo": 235.35,
        "noaa": 263.04,
        "sg": 235.35
      },
      "waveHeight": {
        "dwd": 0.53,
        "icon": 1.42,
        "meteo": 1.65,
        "noaa": 1.73,
        "sg": 1.65
      },
      "wavePeriod": {
        "icon": 4.81,
        "meteo": 4.25,
        "noaa": 6,
        "sg": 4.25
      },
      "windDirection": {
        "icon": 264.05,
        "noaa": 259.25,
        "sg": 264.05
      },
      "windSpeed": {
        "icon": 10.64,
        "noaa": 7.3,
        "sg": 10.64
      }
    },
    {
      "airTemperature": {
        "dwd": 9,
        "noaa": 6.56,
        "sg": 9
      },
      "currentDirection": {
        "meto": 261.46,
        "sg": 261.46
      },
      "currentSpeed": {
        "meto": 0.15,
        "sg": 0.15
      },
      "gust": {
        "dwd": 11.93,
        "noaa": 10.81,
        "sg": 11.93
      },
      "time": "2024-04-28T13:00:00+00:00",
      "visibility": {
        "noaa": 8.1,
        "sg": 8.1
      },
      "waterTemperature": {
        "meto": 10.94,
        "noaa": 7.18,
        "sg": 10.94
      },
      "waveDirection": {
        "icon": 240.96,
        "meteo": 238.97,
        "noaa": 262.32,
        "sg": 238.97
      },
      "waveHeight": {
        "dwd": 0.55,
        "icon": 1.32,
        "meteo": 1.56,
        "noaa": 1.55,
        "sg": 1.56
      },
      "wavePeriod": {
        "icon": 4.87,
        "meteo": 4.25,
        "noaa": 5.76,
        "sg": 4.25
      },
      "windDirection": {
        "icon": 266.67,
        "noaa": 253.66,
        "sg": 266.67
      },
      "windSpeed": {
        "icon": 9.27,
        "noaa": 6.8,
        "sg": 9.27
      }
    }
  ],
  "meta": {
    "cost": 1,
    "dailyQuota": 10,
    "end": "2024-04-28 13:14",
    "lat": 50.8141883,
    "lng": -0.1416837,
    "params": [
      "waterTemperature",
      "windSpeed",
      "windDirection",
      "gust",
      "waveHeight",
      "waveDirection",
      "wavePeriod",
      "visibility",
      "currentDirection",
      "currentSpeed",
      "airTemperature"
    ],
    "requestCount": 5,
    "start": "2024-04-28 12:00"
  }
}
