{
  "hours": [
    {
      "airTemperature": {
        "dwd": 9.8,
        "ecmwf": 9.07,
        "ecmwf:aifs": 9.46,
        "noaa": 6.73,
        "sg": 9.07
      },
      "currentDirection": {
        "ecmwf": 263.87,
        "fcoo": 45.0,
        "metno": 173.8,
        "meto": 238.59,
        "sg": 173.8
      },
      "currentSpeed": {
        "ecmwf": 0.21,
        "fcoo": 7274.61,
        "metno": 0.03,
        "meto": 0.08,
        "sg": 0.03
      },
      "gust": {
        "dwd": 7.96,
        "ecmwf": 8.38,
        "noaa": 5.53,
        "sg": 8.38
      },
      "time": "2025-12-03T09:00:00+00:00",
      "visibility": {
        "noaa": 24.14,
        "sg": 24.14
      },
      "waterTemperature": {
        "metno": 11.04,
        "meto": 10.76,
        "noaa": 6.05,
        "sg": 11.04
      },
      "waveDirection": {
        "ecmwf": 221.76,
        "meteo": 237.99,
        "metno": 207.97,
        "noaa": 246.07,
        "sg": 207.97
      },
      "waveHeight": {
        "dwd": 0.96,
        "ecmwf": 1.05,
        "meteo": 1.37,
        "metno": 0.85,
        "noaa": 1.11,
        "sg": 0.85
      },
      "wavePeriod": {
        "ecmwf": 3.75,
        "meteo": 4.63,
        "noaa": 10.41,
        "sg": 3.75
      },
      "windDirection": {
        "dwd": 227.08,
        "ecmwf": 218.87,
        "ecmwf:aifs": 224.54,
        "noaa": 202.25,
        "sg": 218.87
      },
      "windSpeed": {
        "dwd": 5.13,
        "ecmwf": 5.53,
        "ecmwf:aifs": 5.2,
        "noaa": 2.32,
        "sg": 5.53
      }
    },
    {
      "airTemperature": {
        "dwd": 10.17,
        "ecmwf": 9.11,
        "ecmwf:aifs": 9.53,
        "noaa": 7.62,
        "sg": 9.11
      },
      "currentDirection": {
        "ecmwf": 264.0,
        "fcoo": 45.0,
        "metno": 40.63,
        "meto": 242.35,
        "sg": 40.63
      },
      "currentSpeed": {
        "ecmwf": 0.21,
        "fcoo": 7274.61,
        "metno": 0.17,
        "meto": 0.08,
        "sg": 0.17
      },
      "gust": {
        "dwd": 7.74,
        "ecmwf": 8.32,
        "noaa": 6.29,
        "sg": 8.32
      },
      "time": "2025-12-03T10:00:00+00:00",
      "visibility": {
        "noaa": 20.58,
        "sg": 20.58
      },
      "waterTemperature": {
        "metno": 11.04,
        "meto": 10.77,
        "noaa": 7.24,
        "sg": 11.04
      },
      "waveDirection": {
        "ecmwf": 221.06,
        "meteo": 237.42,
        "metno": 208.55,
        "noaa": 239.52,
        "sg": 208.55
      },
      "waveHeight": {
        "dwd": 0.93,
        "ecmwf": 1.04,
        "meteo": 1.35,
        "metno": 0.83,
        "noaa": 1.1,
        "sg": 0.83
      },
      "wavePeriod": {
        "ecmwf": 3.72,
        "meteo": 4.58,
        "noaa": 8.57,
        "sg": 3.72
      },
      "windDirection": {
        "dwd": 220.89,
        "ecmwf": 217.68,
        "ecmwf:aifs": 221.44,
        "noaa": 206.48,
        "sg": 217.68
      },
      "windSpeed": {
        "dwd": 5.1,
        "ecmwf": 5.83,
        "ecmwf:aifs": 5.25,
        "noaa": 3.3,
        "sg": 5.83
      }
    }
  ],
  "meta": {
    "cost": 1,
    "dailyQuota": 10,
    "end": "2025-12-03 10:00",
    "lat": 50.8141883,
    "lng": -0.1416837,
    "params": [
      "waterTemperature",
      "windSpeed",
      "windDirection",
      "gust",
      "waveHeight",
      "waveDirection",
      "wavePeriod",
      "visibility",
      "currentDirection",
      "currentSpeed",
      "airTemperature"
    ],
    "requestCount": 4,
    "start": "2025-12-03 09:00"
  }
}
