{
  "hours": [
    {
      "airTemperature": {
        "dwd": 12.72,
        "ecmwf": 8.52,
        "noaa": 17.32,
        "sg": 8.52
      },
      "currentDirection": {
        "meto": 71.63,
        "sg": 71.63
      },
      "currentSpeed": {
        "meto": 0.06,
        "sg": 0.06
      },
      "gust": {
        "dwd": 4.6,
        "noaa": 0.85,
        "sg": 4.6
      },
      "time": "2025-04-11T12:00:00+00:00",
      "visibility": {
        "noaa": 24.14,
        "sg": 24.14
      },
      "waterTemperature": {
        "meto": 11.12,
        "noaa": 22.08,
        "sg": 11.12
      },
      "waveDirection": {
        "ecmwf": 241.98,
        "meteo": 251.54,
        "noaa": 244.63,
        "sg": 241.98
      },
      "waveHeight": {
        "dwd": 0.14,
        "ecmwf": 0.24,
        "meteo": 0.33,
        "noaa": 0.22,
        "sg": 0.24
      },
      "wavePeriod": {
        "ecmwf": 6.27,
        "meteo": 6.66,
        "noaa": 10.07,
        "sg": 6.27
      },
      "windDirection": {
        "ecmwf": 178.3,
        "noaa": 176.34,
        "sg": 178.3
      },
      "windSpeed": {
        "ecmwf": 2.61,
        "noaa": 1.11,
        "sg": 2.61
      }
    },
    {
      "airTemperature": {
        "dwd": 12.92,
        "ecmwf": 8.45,
        "noaa": 17.43,
        "sg": 8.45
      },
      "currentDirection": {
        "meto": 91.76,
        "sg": 91.76
      },
      "currentSpeed": {
        "meto": 0.05,
        "sg": 0.05
      },
      "gust": {
        "dwd": 4.03,
        "noaa": 1.12,
        "sg": 4.03
      },
      "time": "2025-04-11T13:00:00+00:00",
      "visibility": {
        "noaa": 24.14,
        "sg": 24.14
      },
      "waterTemperature": {
        "meto": 11.25,
        "noaa": 21.06,
        "sg": 11.25
      },
      "waveDirection": {
        "ecmwf": 240.77,
        "meteo": 251.61,
        "noaa": 244.79,
        "sg": 240.77
      },
      "waveHeight": {
        "dwd": 0.14,
        "ecmwf": 0.24,
        "meteo": 0.32,
        "noaa": 0.22,
        "sg": 0.24
      },
      "wavePeriod": {
        "ecmwf": 5.83,
        "meteo": 6.85,
        "noaa": 10.03,
        "sg": 5.83
      },
      "windDirection": {
        "ecmwf": 172.46,
        "noaa": 175.31,
        "sg": 172.46
      },
      "windSpeed": {
        "ecmwf": 2.18,
        "noaa": 1.42,
        "sg": 2.18
      }
    }
  ],
  "meta": {
    "cost": 1,
    "dailyQuota": 10,
    "end": "2025-04-11 13:00",
    "lat": 50.8141883,
    "lng": -0.1416837,
    "params": [
      "waterTemperature",
      "windSpeed",
      "windDirection",
      "gust",
      "waveHeight",
      "waveDirection",
      "wavePeriod",
      "visibility",
      "currentDirection",
      "currentSpeed",
      "airTemperature"
    ],
    "requestCount": 5,
    "start": "2025-04-11 12:00"
  }
}
