{
  "hours": [
    {
      "airTemperature": {
        "dwd": 19.09,
        "noaa": 19.26,
        "sg": 19.09
      },
      "currentDirection": {
        "meto": 70.08,
        "sg": 70.08
      },
      "currentSpeed": {
        "meto": 0.24,
        "sg": 0.24
      },
      "gust": {
        "dwd": 11.02,
        "noaa": 6.22,
        "sg": 11.02
      },
      "time": "2022-08-28T09:00:00+00:00",
      "visibility": {
        "noaa": 24.14,
        "sg": 24.14
      },
      "waterTemperature": {
        "meto": 20.16,
        "noaa": 20.69,
        "sg": 20.16
      },
      "waveDirection": {
        "icon": 64.01,
        "meteo": 68.62,
        "meto": 148.9,
        "noaa": 77.64,
        "sg": 148.9
      },
      "waveHeight": {
        "dwd": 0.19,
        "icon": 0.43,
        "meteo": 0.88,
        "meto": 0.23,
        "noaa": 0.9,
        "sg": 0.23
      },
      "wavePeriod": {
        "icon": 3.21,
        "meteo": 3.3,
        "meto": 2.29,
        "noaa": 4.4,
        "sg": 2.29
      },
      "windDirection": {
        "icon": 60.67,
        "noaa": 80.4,
        "sg": 60.67
      },
      "windSpeed": {
        "icon": 5.94,
        "noaa": 4.75,
        "sg": 5.94
      }
    },
    {
      "airTemperature": {
        "dwd": 20.01,
        "noaa": 20.42,
        "sg": 20.01
      },
      "currentDirection": {
        "meto": 69.95,
        "sg": 69.95
      },
      "currentSpeed": {
        "meto": 0.23,
        "sg": 0.23
      },
      "gust": {
        "dwd": 11.21,
        "noaa": 6.02,
        "sg": 11.21
      },
      "time": "2022-08-28T10:00:00+00:00",
      "visibility": {
        "noaa": 24.14,
        "sg": 24.14
      },
      "waterTemperature": {
        "meto": 20.15,
        "noaa": 22.32,
        "sg": 20.15
      },
      "waveDirection": {
        "icon": 69.33,
        "meteo": 68.49,
        "meto": 148,
        "noaa": 78.34,
        "sg": 148
      },
      "waveHeight": {
        "dwd": 0.22,
        "icon": 0.48,
        "meteo": 0.86,
        "meto": 0.24,
        "noaa": 0.93,
        "sg": 0.24
      },
      "wavePeriod": {
        "icon": 3.28,
        "meteo": 3.27,
        "meto": 2.28,
        "noaa": 4.49,
        "sg": 2.28
      },
      "windDirection": {
        "icon": 69.45,
        "noaa": 76.71,
        "sg": 69.45
      },
      "windSpeed": {
        "icon": 6.04,
        "noaa": 4.89,
        "sg": 6.04
      }
    }
  ],
  "meta": {
    "cost": 1,
    "dailyQuota": 10,
    "end": "2022-08-28 10:07",
    "lat": 50.8141883,
    "lng": -0.1416837,
    "params": [
      "waterTemperature",
      "windSpeed",
      "windDirection",
      "gust",
      "waveHeight",
      "waveDirection",
      "wavePeriod",
      "visibility",
      "currentDirection",
      "currentSpeed",
      "airTemperature"
    ],
    "requestCount": 4,
    "start": "2022-08-28 09:00"
  }
}
