{
  "hours": [
    {
      "airTemperature": {
        "dwd": 17.95,
        "noaa": 17.51,
        "sg": 17.95
      },
      "currentDirection": {
        "meto": 80.67,
        "sg": 80.67
      },
      "currentSpeed": {
        "meto": 0.11,
        "sg": 0.11
      },
      "gust": {
        "dwd": 11.3,
        "noaa": 7.03,
        "sg": 11.3
      },
      "time": "2024-09-22T09:00:00+00:00",
      "visibility": {
        "noaa": 24.14,
        "sg": 24.14
      },
      "waterTemperature": {
        "meto": 17.65,
        "noaa": 18.21,
        "sg": 17.65
      },
      "waveDirection": {
        "meteo": 121.94,
        "noaa": 109.53,
        "sg": 121.94
      },
      "waveHeight": {
        "dwd": 0.35,
        "meteo": 0.67,
        "noaa": 0.62,
        "sg": 0.67
      },
      "wavePeriod": {
        "meteo": 2.89,
        "noaa": 3.5,
        "sg": 2.89
      },
      "windDirection": {
        "noaa": 115.73,
        "sg": 115.73
      },
      "windSpeed": {
        "noaa": 4.65,
        "sg": 4.65
      }
    },
    {
      "airTemperature": {
        "dwd": 17.88,
        "noaa": 17.92,
        "sg": 17.88
      },
      "currentDirection": {
        "meto": 79.92,
        "sg": 79.92
      },
      "currentSpeed": {
        "meto": 0.11,
        "sg": 0.11
      },
      "gust": {
        "dwd": 10.78,
        "noaa": 6.81,
        "sg": 10.78
      },
      "time": "2024-09-22T10:00:00+00:00",
      "visibility": {
        "noaa": 20.67,
        "sg": 20.67
      },
      "waterTemperature": {
        "meto": 17.67,
        "noaa": 18.92,
        "sg": 17.67
      },
      "waveDirection": {
        "meteo": 130.07,
        "noaa": 112.77,
        "sg": 130.07
      },
      "waveHeight": {
        "dwd": 0.4,
        "meteo": 0.64,
        "noaa": 0.6,
        "sg": 0.64
      },
      "wavePeriod": {
        "meteo": 2.9,
        "noaa": 3.49,
        "sg": 2.9
      },
      "windDirection": {
        "noaa": 128.92,
        "sg": 128.92
      },
      "windSpeed": {
        "noaa": 4.86,
        "sg": 4.86
      }
    }
  ],
  "meta": {
    "cost": 1,
    "dailyQuota": 10,
    "end": "2024-09-22 10:02",
    "lat": 50.8141883,
    "lng": -0.1416837,
    "params": [
      "waterTemperature",
      "windSpeed",
      "windDirection",
      "gust",
      "waveHeight",
      "waveDirection",
      "wavePeriod",
      "visibility",
      "currentDirection",
      "currentSpeed",
      "airTemperature"
    ],
    "requestCount": 4,
    "start": "2024-09-22 09:00"
  }
}
