{
  "hours": [
    {
      "airTemperature": {
        "dwd": 19.72,
        "noaa": 19.4,
        "sg": 19.72
      },
      "currentDirection": {
        "meto": 77.28,
        "sg": 77.28
      },
      "currentSpeed": {
        "meto": 0.09,
        "sg": 0.09
      },
      "gust": {
        "dwd": 3.1,
        "noaa": 2.23,
        "sg": 3.1
      },
      "time": "2024-07-19T06:00:00+00:00",
      "visibility": {
        "noaa": 24.13,
        "sg": 24.13
      },
      "waterTemperature": {
        "meto": 18.13,
        "noaa": 19.65,
        "sg": 18.13
      },
      "waveDirection": {
        "meteo": 232.39,
        "noaa": 251.58,
        "sg": 232.39
      },
      "waveHeight": {
        "dwd": 0.17,
        "meteo": 0.31,
        "noaa": 0.32,
        "sg": 0.31
      },
      "wavePeriod": {
        "meteo": 3.34,
        "noaa": 9.21,
        "sg": 3.34
      },
      "windDirection": {
        "noaa": 108.13,
        "sg": 108.13
      },
      "windSpeed": {
        "noaa": 1.46,
        "sg": 1.46
      }
    },
    {
      "airTemperature": {
        "dwd": 20.61,
        "noaa": 21.13,
        "sg": 20.61
      },
      "currentDirection": {
        "meto": 79.54,
        "sg": 79.54
      },
      "currentSpeed": {
        "meto": 0.11,
        "sg": 0.11
      },
      "gust": {
        "dwd": 4.87,
        "noaa": 2.69,
        "sg": 4.87
      },
      "time": "2024-07-19T07:00:00+00:00",
      "visibility": {
        "noaa": 24.13,
        "sg": 24.13
      },
      "waterTemperature": {
        "meto": 18.17,
        "noaa": 21.99,
        "sg": 18.17
      },
      "waveDirection": {
        "meteo": 237.81,
        "noaa": 251.47,
        "sg": 237.81
      },
      "waveHeight": {
        "dwd": 0.17,
        "meteo": 0.31,
        "noaa": 0.33,
        "sg": 0.31
      },
      "wavePeriod": {
        "meteo": 3.57,
        "noaa": 9.05,
        "sg": 3.57
      },
      "windDirection": {
        "noaa": 117.49,
        "sg": 117.49
      },
      "windSpeed": {
        "noaa": 1.98,
        "sg": 1.98
      }
    }
  ],
  "meta": {
    "cost": 1,
    "dailyQuota": 10,
    "end": "2024-07-19 07:08",
    "lat": 50.8141883,
    "lng": -0.1416837,
    "params": [
      "waterTemperature",
      "windSpeed",
      "windDirection",
      "gust",
      "waveHeight",
      "waveDirection",
      "wavePeriod",
      "visibility",
      "currentDirection",
      "currentSpeed",
      "airTemperature"
    ],
    "requestCount": 3,
    "start": "2024-07-19 06:00"
  }
}
