{
  "hours": [
    {
      "airTemperature": {
        "dwd": 16.49,
        "noaa": 15.13,
        "sg": 16.49
      },
      "currentDirection": {
        "meto": 3.75,
        "sg": 3.75
      },
      "currentSpeed": {
        "meto": 0.07,
        "sg": 0.07
      },
      "gust": {
        "dwd": 3.69,
        "noaa": 1.81,
        "sg": 3.69
      },
      "time": "2024-06-23T21:00:00+00:00",
      "visibility": {
        "noaa": 24.13,
        "sg": 24.13
      },
      "waterTemperature": {
        "meto": 17.23,
        "noaa": 13.7,
        "sg": 17.23
      },
      "waveDirection": {
        "meteo": 254.69,
        "noaa": 249.25,
        "sg": 254.69
      },
      "waveHeight": {
        "dwd": 0.28,
        "meteo": 0.49,
        "noaa": 0.44,
        "sg": 0.49
      },
      "wavePeriod": {
        "meteo": 4.28,
        "noaa": 8.41,
        "sg": 4.28
      },
      "windDirection": {
        "noaa": 217.28,
        "sg": 217.28
      },
      "windSpeed": {
        "noaa": 1.89,
        "sg": 1.89
      }
    },
    {
      "airTemperature": {
        "dwd": 16.35,
        "noaa": 15.32,
        "sg": 16.35
      },
      "currentDirection": {
        "meto": 13.74,
        "sg": 13.74
      },
      "currentSpeed": {
        "meto": 0.08,
        "sg": 0.08
      },
      "gust": {
        "dwd": 2.28,
        "noaa": 1.65,
        "sg": 2.28
      },
      "time": "2024-06-23T22:00:00+00:00",
      "visibility": {
        "noaa": 24.13,
        "sg": 24.13
      },
      "waterTemperature": {
        "meto": 17.19,
        "noaa": 14.18,
        "sg": 17.19
      },
      "waveDirection": {
        "meteo": 254.64,
        "noaa": 249.41,
        "sg": 254.64
      },
      "waveHeight": {
        "dwd": 0.27,
        "meteo": 0.48,
        "noaa": 0.43,
        "sg": 0.48
      },
      "wavePeriod": {
        "meteo": 4.47,
        "noaa": 8.4,
        "sg": 4.47
      },
      "windDirection": {
        "noaa": 218.95,
        "sg": 218.95
      },
      "windSpeed": {
        "noaa": 1.72,
        "sg": 1.72
      }
    }
  ],
  "meta": {
    "cost": 1,
    "dailyQuota": 10,
    "end": "2024-06-23 22:03",
    "lat": 50.8141883,
    "lng": -0.1416837,
    "params": [
      "waterTemperature",
      "windSpeed",
      "windDirection",
      "gust",
      "waveHeight",
      "waveDirection",
      "wavePeriod",
      "visibility",
      "currentDirection",
      "currentSpeed",
      "airTemperature"
    ],
    "requestCount": 8,
    "start": "2024-06-23 21:00"
  }
}
