{
  "hours": [
    {
      "airTemperature": {
        "dwd": 15.44,
        "noaa": 10.41,
        "sg": 15.44
      },
      "currentDirection": {
        "meto": 78.63,
        "sg": 78.63
      },
      "currentSpeed": {
        "meto": 0.22,
        "sg": 0.22
      },
      "gust": {
        "dwd": 4.44,
        "noaa": 1.88,
        "sg": 4.44
      },
      "time": "2024-07-03T01:00:00+00:00",
      "visibility": {
        "noaa": 21.06,
        "sg": 21.06
      },
      "waterTemperature": {
        "meto": 17.13,
        "noaa": 9.46,
        "sg": 17.13
      },
      "waveDirection": {
        "meteo": 256.52,
        "noaa": 256.51,
        "sg": 256.52
      },
      "waveHeight": {
        "dwd": 0.11,
        "meteo": 0.4,
        "noaa": 0.35,
        "sg": 0.4
      },
      "wavePeriod": {
        "meteo": 3.63,
        "noaa": 4.42,
        "sg": 3.63
      },
      "windDirection": {
        "noaa": 296.2,
        "sg": 296.2
      },
      "windSpeed": {
        "noaa": 1.74,
        "sg": 1.74
      }
    },
    {
      "airTemperature": {
        "dwd": 14.82,
        "noaa": 10.58,
        "sg": 14.82
      },
      "currentDirection": {
        "meto": 75.62,
        "sg": 75.62
      },
      "currentSpeed": {
        "meto": 0.19,
        "sg": 0.19
      },
      "gust": {
        "dwd": 4.31,
        "noaa": 2.05,
        "sg": 4.31
      },
      "time": "2024-07-03T02:00:00+00:00",
      "visibility": {
        "noaa": 17.99,
        "sg": 17.99
      },
      "waterTemperature": {
        "meto": 17.09,
        "noaa": 9.82,
        "sg": 17.09
      },
      "waveDirection": {
        "meteo": 255.88,
        "noaa": 257.67,
        "sg": 255.88
      },
      "waveHeight": {
        "dwd": 0.12,
        "meteo": 0.4,
        "noaa": 0.35,
        "sg": 0.4
      },
      "wavePeriod": {
        "meteo": 3.66,
        "noaa": 4.46,
        "sg": 3.66
      },
      "windDirection": {
        "noaa": 290.23,
        "sg": 290.23
      },
      "windSpeed": {
        "noaa": 1.79,
        "sg": 1.79
      }
    }
  ],
  "meta": {
    "cost": 1,
    "dailyQuota": 10,
    "end": "2024-07-03 02:10",
    "lat": 50.8141883,
    "lng": -0.1416837,
    "params": [
      "waterTemperature",
      "windSpeed",
      "windDirection",
      "gust",
      "waveHeight",
      "waveDirection",
      "wavePeriod",
      "visibility",
      "currentDirection",
      "currentSpeed",
      "airTemperature"
    ],
    "requestCount": 1,
    "start": "2024-07-03 01:00"
  }
}
