{
  "hours": [
    {
      "airTemperature": {
        "dwd": 16.87,
        "ecmwf": 15.4,
        "ecmwf:aifs": 17.36,
        "noaa": 18.97,
        "sg": 15.4
      },
      "currentDirection": {
        "ecmwf": 88.29,
        "metno": 204.49,
        "meto": 74.6,
        "sg": 204.49
      },
      "currentSpeed": {
        "ecmwf": 0.18,
        "metno": 0.09,
        "meto": 0.06,
        "sg": 0.09
      },
      "gust": {
        "dwd": 9.61,
        "noaa": 6.3,
        "sg": 9.61
      },
      "time": "2025-08-21T09:00:00+00:00",
      "visibility": {
        "noaa": 24.14,
        "sg": 24.14
      },
      "waterTemperature": {
        "metno": 19.26,
        "meto": 20.1,
        "noaa": 22.59,
        "sg": 19.26
      },
      "waveDirection": {
        "ecmwf": 6.19,
        "meteo": 33.06,
        "metno": 100.01,
        "noaa": 74.44,
        "sg": 100.01
      },
      "waveHeight": {
        "dwd": 0.44,
        "ecmwf": 0.47,
        "meteo": 0.86,
        "metno": 0.16,
        "noaa": 0.84,
        "sg": 0.16
      },
      "wavePeriod": {
        "ecmwf": 2.08,
        "meteo": 3.29,
        "noaa": 4.97,
        "sg": 2.08
      },
      "windDirection": {
        "dwd": 12.67,
        "ecmwf": 12.42,
        "ecmwf:aifs": 17.28,
        "noaa": 13.69,
        "sg": 12.42
      },
      "windSpeed": {
        "dwd": 7.14,
        "ecmwf": 6.18,
        "ecmwf:aifs": 6.22,
        "noaa": 5.87,
        "sg": 6.18
      }
    },
    {
      "airTemperature": {
        "dwd": 17.47,
        "ecmwf": 15.9,
        "ecmwf:aifs": 17.88,
        "noaa": 18.74,
        "sg": 15.9
      },
      "currentDirection": {
        "ecmwf": 87.07,
        "metno": 42.24,
        "meto": 71.67,
        "sg": 42.24
      },
      "currentSpeed": {
        "ecmwf": 0.19,
        "metno": 0.1,
        "meto": 0.07,
        "sg": 0.1
      },
      "gust": {
        "dwd": 9.67,
        "noaa": 6.39,
        "sg": 9.67
      },
      "time": "2025-08-21T10:00:00+00:00",
      "visibility": {
        "noaa": 24.14,
        "sg": 24.14
      },
      "waterTemperature": {
        "metno": 19.22,
        "meto": 20.13,
        "noaa": 21.81,
        "sg": 19.22
      },
      "waveDirection": {
        "ecmwf": 10.4,
        "meteo": 36.26,
        "metno": 102.58,
        "noaa": 73.19,
        "sg": 102.58
      },
      "waveHeight": {
        "dwd": 0.42,
        "ecmwf": 0.43,
        "meteo": 0.82,
        "metno": 0.16,
        "noaa": 0.78,
        "sg": 0.16
      },
      "wavePeriod": {
        "ecmwf": 2.02,
        "meteo": 3.32,
        "noaa": 4.91,
        "sg": 2.02
      },
      "windDirection": {
        "dwd": 16.52,
        "ecmwf": 14.17,
        "ecmwf:aifs": 19.04,
        "noaa": 14.94,
        "sg": 14.17
      },
      "windSpeed": {
        "dwd": 6.74,
        "ecmwf": 5.94,
        "ecmwf:aifs": 5.72,
        "noaa": 6.05,
        "sg": 5.94
      }
    }
  ],
  "meta": {
    "cost": 1,
    "dailyQuota": 10,
    "end": "2025-08-21 10:00",
    "lat": 50.8141883,
    "lng": -0.1416837,
    "params": [
      "waterTemperature",
      "windSpeed",
      "windDirection",
      "gust",
      "waveHeight",
      "waveDirection",
      "wavePeriod",
      "visibility",
      "currentDirection",
      "currentSpeed",
      "airTemperature"
    ],
    "requestCount": 4,
    "start": "2025-08-21 09:00"
  }
}
