{
  "hours": [
    {
      "airTemperature": {
        "dwd": 17.13,
        "noaa": 15.63,
        "sg": 17.13
      },
      "currentDirection": {
        "meto": 245.18,
        "sg": 245.18
      },
      "currentSpeed": {
        "meto": 0.14,
        "sg": 0.14
      },
      "gust": {
        "dwd": 12.52,
        "noaa": 11.75,
        "sg": 12.52
      },
      "time": "2023-10-19T15:00:00+00:00",
      "visibility": {
        "noaa": 9.61,
        "sg": 9.61
      },
      "waterTemperature": {
        "meto": 16.41,
        "noaa": 15.63,
        "sg": 16.41
      },
      "waveDirection": {
        "icon": 183.64,
        "meteo": 200.66,
        "noaa": 190.85,
        "sg": 200.66
      },
      "waveHeight": {
        "dwd": 1.26,
        "icon": 1.51,
        "meteo": 1.51,
        "noaa": 1.74,
        "sg": 1.51
      },
      "wavePeriod": {
        "icon": 5.63,
        "meteo": 4.49,
        "noaa": 5.67,
        "sg": 4.49
      },
      "windDirection": {
        "icon": 168.6,
        "noaa": 173.37,
        "sg": 168.6
      },
      "windSpeed": {
        "icon": 7.42,
        "noaa": 7.02,
        "sg": 7.42
      }
    },
    {
      "airTemperature": {
        "dwd": 16.85,
        "noaa": 15.19,
        "sg": 16.85
      },
      "currentDirection": {
        "meto": 244.43,
        "sg": 244.43
      },
      "currentSpeed": {
        "meto": 0.13,
        "sg": 0.13
      },
      "gust": {
        "dwd": 11.34,
        "noaa": 11.64,
        "sg": 11.34
      },
      "time": "2023-10-19T16:00:00+00:00",
      "visibility": {
        "noaa": 11.66,
        "sg": 11.66
      },
      "waterTemperature": {
        "meto": 16.41,
        "noaa": 14.81,
        "sg": 16.41
      },
      "waveDirection": {
        "icon": 184.38,
        "meteo": 200.1,
        "noaa": 193.86,
        "sg": 200.1
      },
      "waveHeight": {
        "dwd": 1.17,
        "icon": 1.47,
        "meteo": 1.47,
        "noaa": 1.67,
        "sg": 1.47
      },
      "wavePeriod": {
        "icon": 5.59,
        "meteo": 4.4,
        "noaa": 5.66,
        "sg": 4.4
      },
      "windDirection": {
        "icon": 171.66,
        "noaa": 173.49,
        "sg": 171.66
      },
      "windSpeed": {
        "icon": 7.46,
        "noaa": 6.58,
        "sg": 7.46
      }
    }
  ],
  "meta": {
    "cost": 1,
    "dailyQuota": 10,
    "end": "2023-10-19 16:02",
    "lat": 50.8141883,
    "lng": -0.1416837,
    "params": [
      "waterTemperature",
      "windSpeed",
      "windDirection",
      "gust",
      "waveHeight",
      "waveDirection",
      "wavePeriod",
      "visibility",
      "currentDirection",
      "currentSpeed",
      "airTemperature"
    ],
    "requestCount": 6,
    "start": "2023-10-19 15:00"
  }
}
