{
  "hours": [
    {
      "airTemperature": {
        "dwd": 10.61,
        "noaa": 7.99,
        "sg": 10.61
      },
      "currentDirection": {
        "meto": 220.49,
        "sg": 220.49
      },
      "currentSpeed": {
        "meto": 0.05,
        "sg": 0.05
      },
      "gust": {
        "dwd": 9.34,
        "noaa": 11.89,
        "sg": 9.34
      },
      "time": "2023-10-14T01:00:00+00:00",
      "visibility": {
        "noaa": 24.14,
        "sg": 24.14
      },
      "waterTemperature": {
        "meto": 17.8,
        "noaa": 7.17,
        "sg": 17.8
      },
      "waveDirection": {
        "icon": 227.13,
        "meteo": 256.29,
        "noaa": 244.33,
        "sg": 256.29
      },
      "waveHeight": {
        "dwd": 0.88,
        "icon": 1.19,
        "meteo": 1.99,
        "noaa": 1.72,
        "sg": 1.99
      },
      "wavePeriod": {
        "icon": 6.95,
        "meteo": 5.24,
        "noaa": 6.88,
        "sg": 5.24
      },
      "windDirection": {
        "icon": 294.29,
        "noaa": 299,
        "sg": 294.29
      },
      "windSpeed": {
        "icon": 5.73,
        "noaa": 4.69,
        "sg": 5.73
      }
    }
  ],
  "meta": {
    "cost": 1,
    "dailyQuota": 10,
    "end": "2023-10-14 01:58",
    "lat": 50.8141883,
    "lng": -0.1416837,
    "params": [
      "waterTemperature",
      "windSpeed",
      "windDirection",
      "gust",
      "waveHeight",
      "waveDirection",
      "wavePeriod",
      "visibility",
      "currentDirection",
      "currentSpeed",
      "airTemperature"
    ],
    "requestCount": 1,
    "start": "2023-10-14 01:00"
  }
}
