{
  "hours": [
    {
      "airTemperature": {
        "dwd": 5.05,
        "ecmwf": 4.11,
        "ecmwf:aifs": 4.7,
        "noaa": 2.44,
        "sg": 4.11
      },
      "currentDirection": {
        "ecmwf": 80.6,
        "fcoo": 45.0,
        "metno": 24.44,
        "meto": 61.26,
        "sg": 24.44
      },
      "currentSpeed": {
        "ecmwf": 0.26,
        "fcoo": 7274.61,
        "metno": 0.31,
        "meto": 0.04,
        "sg": 0.31
      },
      "gust": {
        "dwd": 10.35,
        "ecmwf": 10.75,
        "noaa": 8.9,
        "sg": 10.75
      },
      "time": "2025-11-20T15:00:00+00:00",
      "visibility": {
        "noaa": 24.14,
        "sg": 24.14
      },
      "waterTemperature": {
        "metno": 12.01,
        "meto": 12.22,
        "noaa": 2.35,
        "sg": 12.01
      },
      "waveDirection": {
        "ecmwf": 313.56,
        "meteo": 317.45,
        "metno": 270.34,
        "noaa": 306.06,
        "sg": 270.34
      },
      "waveHeight": {
        "dwd": 0.56,
        "ecmwf": 0.65,
        "meteo": 0.86,
        "metno": 0.26,
        "noaa": 0.86,
        "sg": 0.26
      },
      "wavePeriod": {
        "ecmwf": 2.35,
        "meteo": 3.21,
        "noaa": 3.88,
        "sg": 2.35
      },
      "windDirection": {
        "dwd": 330.68,
        "ecmwf": 334.05,
        "ecmwf:aifs": 329.77,
        "noaa": 330.93,
        "sg": 334.05
      },
      "windSpeed": {
        "dwd": 7.34,
        "ecmwf": 7.34,
        "ecmwf:aifs": 8.09,
        "noaa": 4.54,
        "sg": 7.34
      }
    },
    {
      "airTemperature": {
        "dwd": 5.01,
        "ecmwf": 4.21,
        "ecmwf:aifs": 4.87,
        "noaa": 1.53,
        "sg": 4.21
      },
      "currentDirection": {
        "ecmwf": 81.01,
        "fcoo": 45.0,
        "metno": 19.14,
        "meto": 62.68,
        "sg": 19.14
      },
      "currentSpeed": {
        "ecmwf": 0.26,
        "fcoo": 7274.61,
        "metno": 0.19,
        "meto": 0.05,
        "sg": 0.19
      },
      "gust": {
        "dwd": 9.77,
        "ecmwf": 11.62,
        "noaa": 8.58,
        "sg": 11.62
      },
      "time": "2025-11-20T16:00:00+00:00",
      "visibility": {
        "noaa": 24.14,
        "sg": 24.14
      },
      "waterTemperature": {
        "metno": 11.99,
        "meto": 12.2,
        "noaa": 0.99,
        "sg": 11.99
      },
      "waveDirection": {
        "ecmwf": 317.25,
        "meteo": 320.07,
        "metno": 275.38,
        "noaa": 312.81,
        "sg": 275.38
      },
      "waveHeight": {
        "dwd": 0.54,
        "ecmwf": 0.66,
        "meteo": 0.88,
        "metno": 0.25,
        "noaa": 0.85,
        "sg": 0.25
      },
      "wavePeriod": {
        "ecmwf": 2.35,
        "meteo": 3.22,
        "noaa": 3.87,
        "sg": 2.35
      },
      "windDirection": {
        "dwd": 329.85,
        "ecmwf": 335.62,
        "ecmwf:aifs": 331.6,
        "noaa": 324.5,
        "sg": 335.62
      },
      "windSpeed": {
        "dwd": 7.33,
        "ecmwf": 7.36,
        "ecmwf:aifs": 8.27,
        "noaa": 4.05,
        "sg": 7.36
      }
    }
  ],
  "meta": {
    "cost": 1,
    "dailyQuota": 10,
    "end": "2025-11-20 16:00",
    "lat": 50.8141883,
    "lng": -0.1416837,
    "params": [
      "waterTemperature",
      "windSpeed",
      "windDirection",
      "gust",
      "waveHeight",
      "waveDirection",
      "wavePeriod",
      "visibility",
      "currentDirection",
      "currentSpeed",
      "airTemperature"
    ],
    "requestCount": 6,
    "start": "2025-11-20 15:00"
  }
}
