{
  "hours": [
    {
      "airTemperature": {
        "dwd": 20.5,
        "noaa": 23.87,
        "sg": 20.5
      },
      "currentDirection": {
        "meto": 277.77,
        "sg": 277.77
      },
      "currentSpeed": {
        "meto": 0.12,
        "sg": 0.12
      },
      "gust": {
        "dwd": 14.11,
        "noaa": 5.84,
        "sg": 14.11
      },
      "time": "2024-08-18T15:00:00+00:00",
      "visibility": {
        "noaa": 24.14,
        "sg": 24.14
      },
      "waterTemperature": {
        "meto": 19.42,
        "noaa": 27.43,
        "sg": 19.42
      },
      "waveDirection": {
        "meteo": 253.72,
        "noaa": 252.35,
        "sg": 253.72
      },
      "waveHeight": {
        "dwd": 0.54,
        "meteo": 0.99,
        "noaa": 0.9,
        "sg": 0.99
      },
      "wavePeriod": {
        "meteo": 3.44,
        "noaa": 4.25,
        "sg": 3.44
      },
      "windDirection": {
        "noaa": 266.2,
        "sg": 266.2
      },
      "windSpeed": {
        "noaa": 4.86,
        "sg": 4.86
      }
    },
    {
      "airTemperature": {
        "dwd": 19.8,
        "noaa": 23.2,
        "sg": 19.8
      },
      "currentDirection": {
        "meto": 273.24,
        "sg": 273.24
      },
      "currentSpeed": {
        "meto": 0.14,
        "sg": 0.14
      },
      "gust": {
        "dwd": 13.83,
        "noaa": 5.77,
        "sg": 13.83
      },
      "time": "2024-08-18T16:00:00+00:00",
      "visibility": {
        "noaa": 24.14,
        "sg": 24.14
      },
      "waterTemperature": {
        "meto": 19.35,
        "noaa": 25.45,
        "sg": 19.35
      },
      "waveDirection": {
        "meteo": 253.7,
        "noaa": 253.47,
        "sg": 253.7
      },
      "waveHeight": {
        "dwd": 0.8,
        "meteo": 1.02,
        "noaa": 0.96,
        "sg": 1.02
      },
      "wavePeriod": {
        "meteo": 3.5,
        "noaa": 4.39,
        "sg": 3.5
      },
      "windDirection": {
        "noaa": 271.8,
        "sg": 271.8
      },
      "windSpeed": {
        "noaa": 4.32,
        "sg": 4.32
      }
    }
  ],
  "meta": {
    "cost": 1,
    "dailyQuota": 10,
    "end": "2024-08-18 16:04",
    "lat": 50.8141883,
    "lng": -0.1416837,
    "params": [
      "waterTemperature",
      "windSpeed",
      "windDirection",
      "gust",
      "waveHeight",
      "waveDirection",
      "wavePeriod",
      "visibility",
      "currentDirection",
      "currentSpeed",
      "airTemperature"
    ],
    "requestCount": 6,
    "start": "2024-08-18 15:00"
  }
}
