{
  "hours": [
    {
      "airTemperature": {
        "dwd": 4.79,
        "noaa": 2.19,
        "sg": 4.79
      },
      "currentDirection": {
        "meto": 53.41,
        "sg": 53.41
      },
      "currentSpeed": {
        "meto": 0.05,
        "sg": 0.05
      },
      "gust": {
        "dwd": 12.46,
        "noaa": 12.42,
        "sg": 12.46
      },
      "time": "2024-03-23T06:00:00+00:00",
      "visibility": {
        "noaa": 24.13,
        "sg": 24.13
      },
      "waterTemperature": {
        "meto": 9.63,
        "noaa": 1.35,
        "sg": 9.63
      },
      "waveDirection": {
        "icon": 259.32,
        "meteo": 266.23,
        "noaa": 258.58,
        "sg": 266.23
      },
      "waveHeight": {
        "dwd": 0.77,
        "icon": 1.18,
        "meteo": 1.64,
        "noaa": 1.64,
        "sg": 1.64
      },
      "wavePeriod": {
        "icon": 5.05,
        "meteo": 4.31,
        "noaa": 5.9,
        "sg": 4.31
      },
      "windDirection": {
        "icon": 282.17,
        "noaa": 271.27,
        "sg": 282.17
      },
      "windSpeed": {
        "icon": 8.78,
        "noaa": 5.04,
        "sg": 8.78
      }
    },
    {
      "airTemperature": {
        "dwd": 5.01,
        "noaa": 3.39,
        "sg": 5.01
      },
      "currentDirection": {
        "meto": 44.8,
        "sg": 44.8
      },
      "currentSpeed": {
        "meto": 0.05,
        "sg": 0.05
      },
      "gust": {
        "dwd": 14.33,
        "noaa": 12.25,
        "sg": 14.33
      },
      "time": "2024-03-23T07:00:00+00:00",
      "visibility": {
        "noaa": 24.13,
        "sg": 24.13
      },
      "waterTemperature": {
        "meto": 9.61,
        "noaa": 3.15,
        "sg": 9.61
      },
      "waveDirection": {
        "icon": 259.19,
        "meteo": 265.13,
        "noaa": 258.49,
        "sg": 265.13
      },
      "waveHeight": {
        "dwd": 0.83,
        "icon": 1.27,
        "meteo": 1.73,
        "noaa": 1.7,
        "sg": 1.73
      },
      "wavePeriod": {
        "icon": 5.11,
        "meteo": 4.41,
        "noaa": 5.99,
        "sg": 4.41
      },
      "windDirection": {
        "icon": 282.56,
        "noaa": 273.13,
        "sg": 282.56
      },
      "windSpeed": {
        "icon": 9.22,
        "noaa": 6.02,
        "sg": 9.22
      }
    }
  ],
  "meta": {
    "cost": 1,
    "dailyQuota": 10,
    "end": "2024-03-23 07:04",
    "lat": 50.8141883,
    "lng": -0.1416837,
    "params": [
      "waterTemperature",
      "windSpeed",
      "windDirection",
      "gust",
      "waveHeight",
      "waveDirection",
      "wavePeriod",
      "visibility",
      "currentDirection",
      "currentSpeed",
      "airTemperature"
    ],
    "requestCount": 3,
    "start": "2024-03-23 06:00"
  }
}
