{
  "hours": [
    {
      "airTemperature": {
        "dwd": 15.97,
        "ecmwf": 16.3,
        "ecmwf:aifs": 15.84,
        "noaa": 12.35,
        "sg": 16.3
      },
      "currentDirection": {
        "ecmwf": 87.37,
        "metno": 152.01,
        "meto": 241.63,
        "sg": 152.01
      },
      "currentSpeed": {
        "ecmwf": 0.08,
        "metno": 0.03,
        "meto": 0.09,
        "sg": 0.03
      },
      "gust": {
        "dwd": 6.24,
        "ecmwf": 7.03,
        "noaa": 5.18,
        "sg": 7.03
      },
      "time": "2025-09-28T02:00:00+00:00",
      "visibility": {
        "noaa": 24.13,
        "sg": 24.13
      },
      "waterTemperature": {
        "metno": 16.43,
        "meto": 16.89,
        "noaa": 11.07,
        "sg": 16.43
      },
      "waveDirection": {
        "ecmwf": 208.35,
        "meteo": 228.73,
        "metno": 206.84,
        "noaa": 223.52,
        "sg": 206.84
      },
      "waveHeight": {
        "dwd": 0.56,
        "ecmwf": 0.54,
        "meteo": 0.59,
        "metno": 0.43,
        "noaa": 0.61,
        "sg": 0.43
      },
      "wavePeriod": {
        "ecmwf": 2.57,
        "meteo": 3.28,
        "noaa": 7.48,
        "sg": 2.57
      },
      "windDirection": {
        "dwd": 196.36,
        "ecmwf": 185.25,
        "ecmwf:aifs": 181.16,
        "noaa": 141.07,
        "sg": 185.25
      },
      "windSpeed": {
        "dwd": 4.61,
        "ecmwf": 5.4,
        "ecmwf:aifs": 6.09,
        "noaa": 2.46,
        "sg": 5.4
      }
    }
  ],
  "meta": {
    "cost": 1,
    "dailyQuota": 10,
    "end": "2025-09-28 02:00",
    "lat": 50.8141883,
    "lng": -0.1416837,
    "params": [
      "waterTemperature",
      "windSpeed",
      "windDirection",
      "gust",
      "waveHeight",
      "waveDirection",
      "wavePeriod",
      "visibility",
      "currentDirection",
      "currentSpeed",
      "airTemperature"
    ],
    "requestCount": 1,
    "start": "2025-09-28 02:00"
  }
}
